odoo/addons/shopfloor_mobile_base/README.rst
odoo/addons/shopfloor_mobile_base/__init__.py
odoo/addons/shopfloor_mobile_base/__manifest__.py
odoo/addons/shopfloor_mobile_base/utils.py
odoo/addons/shopfloor_mobile_base/controllers/__init__.py
odoo/addons/shopfloor_mobile_base/controllers/main.py
odoo/addons/shopfloor_mobile_base/i18n/es_AR.po
odoo/addons/shopfloor_mobile_base/i18n/it.po
odoo/addons/shopfloor_mobile_base/i18n/shopfloor_mobile_base.pot
odoo/addons/shopfloor_mobile_base/readme/CONTRIBUTORS.rst
odoo/addons/shopfloor_mobile_base/readme/CREDITS.rst
odoo/addons/shopfloor_mobile_base/readme/DESCRIPTION.rst
odoo/addons/shopfloor_mobile_base/readme/HISTORY.rst
odoo/addons/shopfloor_mobile_base/readme/ROADMAP.rst
odoo/addons/shopfloor_mobile_base/readme/USAGE.rst
odoo/addons/shopfloor_mobile_base/static/description/icon.png
odoo/addons/shopfloor_mobile_base/static/description/index.html
odoo/addons/shopfloor_mobile_base/static/wms/.gitignore
odoo/addons/shopfloor_mobile_base/static/wms/src/fetch.js
odoo/addons/shopfloor_mobile_base/static/wms/src/homepage.js
odoo/addons/shopfloor_mobile_base/static/wms/src/loginpage.js
odoo/addons/shopfloor_mobile_base/static/wms/src/main.js
odoo/addons/shopfloor_mobile_base/static/wms/src/mixin.js
odoo/addons/shopfloor_mobile_base/static/wms/src/router.js
odoo/addons/shopfloor_mobile_base/static/wms/src/theme.js
odoo/addons/shopfloor_mobile_base/static/wms/src/utils.js
odoo/addons/shopfloor_mobile_base/static/wms/src/assets/logo.png
odoo/addons/shopfloor_mobile_base/static/wms/src/assets/icons/android-icon-144x144.png
odoo/addons/shopfloor_mobile_base/static/wms/src/assets/icons/android-icon-192x192.png
odoo/addons/shopfloor_mobile_base/static/wms/src/assets/icons/android-icon-36x36.png
odoo/addons/shopfloor_mobile_base/static/wms/src/assets/icons/android-icon-48x48.png
odoo/addons/shopfloor_mobile_base/static/wms/src/assets/icons/android-icon-72x72.png
odoo14_addon_shopfloor_mobile_base-14.0.3.20.0.dist-info/METADATA
odoo14_addon_shopfloor_mobile_base-14.0.3.20.0.dist-info/WHEEL
odoo14_addon_shopfloor_mobile_base-14.0.3.20.0.dist-info/top_level.txt
odoo14_addon_shopfloor_mobile_base-14.0.3.20.0.dist-info/RECORD
