Metadata-Version: 2.1
Name: odoo14-addon-shopfloor-mobile-base
Version: 14.0.3.20.0
Summary: Mobile frontend for WMS Shopfloor app
Home-page: https://github.com/OCA/wms
Author: Camptocamp, BCIM, Akretion, Odoo Community Association (OCA)
Author-email: support@odoo-community.org
License: LGPL-3
Platform: UNKNOWN
Classifier: Programming Language :: Python
Classifier: Framework :: Odoo
Classifier: Framework :: Odoo :: 14.0
Classifier: License :: OSI Approved :: GNU Lesser General Public License v3 (LGPLv3)
Classifier: Development Status :: 4 - Beta
Requires-Python: >=3.6
Requires-Dist: odoo14-addon-shopfloor-base
Requires-Dist: odoo <14.1dev,>=14.0a
